{"cameraMode":{"drawMode":0,"name":"Shaded","section":"Shading Mode"},"sceneLighting":true,"audioPlay":false,"sceneViewState":{"m_AlwaysRefresh":false,"showFog":true,"showSkybox":true,"showFlares":true,"showImageEffects":true,"showParticleSystems":true,"showVisualEffectGraphs":true,"m_FxEnabled":true},"in2DMode":false,"pivot":{"x":120.0418701171875,"y":-8.185882568359375,"z":-5.214778423309326},"rotation":{"x":-0.3883681297302246,"y":0.5803559422492981,"z":-0.36592569947242739,"w":-0.6153085231781006},"size":1.184268832206726,"orthographic":false}